d2/__init__.py
d2/__main__.py
d2/_crypto.py
d2/cache.py
d2/context.py
d2/decorator.py
d2/exceptions.py
d2/jwks_cache.py
d2/listener.py
d2/middleware.py
d2/policy_client.py
d2/py.typed
d2/state.py
d2/telemetry.py
d2/threads.py
d2/utils.py
d2/validator.py
d2/cli/__init__.py
d2/cli/commands.py
d2/cli/discovery.py
d2/cli/main.py
d2/policy/__init__.py
d2/policy/bundle.py
d2/policy/files.py
d2/policy/manager.py
d2/policy/loaders/__init__.py
d2/policy/loaders/base.py
d2/policy/loaders/cloud.py
d2/policy/loaders/file.py
d2/runtime/__init__.py
d2/runtime/guard.py
d2/runtime/input_validation.py
d2/runtime/output_filter.py
d2/runtime/sequence.py
d2/sanitization/__init__.py
d2/sanitization/output.py
d2/telemetry/__init__.py
d2/telemetry/metrics.py
d2/telemetry/plan_limits.py
d2/telemetry/runtime.py
d2/telemetry/usage.py
d2/validation/__init__.py
d2/validation/base.py
d2/validation/constraints.py
d2/validation/input.py
d2/validation/output.py
d2_sdk-1.2.2.dist-info/licenses/LICENSE
d2_sdk-1.2.2.dist-info/licenses/NOTICE
d2_sdk-1.2.2.dist-info/licenses/NOTICE.header
d2_sdk-1.2.2.dist-info/licenses/NOTICE.third_party
d2_sdk-1.2.2.dist-info/METADATA
d2_sdk-1.2.2.dist-info/WHEEL
d2_sdk-1.2.2.dist-info/entry_points.txt
d2_sdk-1.2.2.dist-info/top_level.txt
d2_sdk-1.2.2.dist-info/RECORD
