Metadata-Version: 2.4
Name: d2-sdk
Version: 1.2.2
Summary: The D2 Python SDK for RBAC on LLM Tools and other functionality
Author-email: David <david@artoo.love>, Daniel <daniel@artoo.love>
License-Expression: BUSL-1.1
Project-URL: Homepage, https://artoo.love/
Project-URL: Repository, https://github.com/artoo-corporation/D2-Python
Project-URL: Bug Tracker, https://github.com/artoo-corporation/D2-Python/issues
Project-URL: Documentation, https://www.artoo.love/documentation/quick-start
Project-URL: Changelog, https://github.com/artoo-corporation/D2-Python/releases
Classifier: Development Status :: 5 - Production/Stable
Classifier: Intended Audience :: Developers
Classifier: Intended Audience :: Information Technology
Classifier: Operating System :: OS Independent
Classifier: Programming Language :: Python :: 3 :: Only
Classifier: Programming Language :: Python :: 3.9
Classifier: Programming Language :: Python :: 3.10
Classifier: Programming Language :: Python :: 3.11
Classifier: Programming Language :: Python :: 3.12
Classifier: Topic :: Security
Classifier: Topic :: Software Development :: Libraries :: Python Modules
Classifier: Typing :: Typed
Requires-Python: >=3.9
License-File: LICENSE
License-File: NOTICE
License-File: NOTICE.header
License-File: NOTICE.third_party
Requires-Dist: httpx
Requires-Dist: anyio
Requires-Dist: PyJWT[crypto]
Requires-Dist: opentelemetry-api
Requires-Dist: PyNaCl
Provides-Extra: dev
Requires-Dist: pytest>=7.0.0; extra == "dev"
Requires-Dist: pytest-asyncio>=0.20.0; extra == "dev"
Requires-Dist: pytest-httpserver>=1.0.0; extra == "dev"
Requires-Dist: pip-tools>=7.0.0; extra == "dev"
Provides-Extra: local
Requires-Dist: watchdog; extra == "local"
Provides-Extra: cli
Requires-Dist: PyYAML; extra == "cli"
Provides-Extra: all
Requires-Dist: watchdog; extra == "all"
Requires-Dist: PyYAML; extra == "all"
Dynamic: license-file
